langchain_vectorize/__init__.py
langchain_vectorize/retrievers.py
langchain_vectorize-0.0.3.dist-info/METADATA
langchain_vectorize-0.0.3.dist-info/WHEEL
langchain_vectorize-0.0.3.dist-info/RECORD
