Metadata-Version: 2.4
Name: langchain-vectorize
Version: 0.0.3
Summary: An integration package connecting Vectorize and LangChain
Project-URL: Repository, https://github.com/vectorize-io/integrations-python.git
Project-URL: Issues, https://github.com/vectorize-io/integrations-python/issues
Author-email: Vectorize <contact@vectorize.io>
License-Expression: MIT
Keywords: langchain,retrieval,search,vectorize
Classifier: Development Status :: 3 - Alpha
Classifier: Intended Audience :: Developers
Classifier: License :: OSI Approved :: MIT License
Classifier: Programming Language :: Python :: 3.9
Classifier: Programming Language :: Python :: 3.10
Classifier: Programming Language :: Python :: 3.11
Classifier: Programming Language :: Python :: 3.12
Classifier: Programming Language :: Python :: 3.13
Classifier: Topic :: Software Development :: Build Tools
Requires-Python: >=3.9
Requires-Dist: langchain-core>=0.3.45
Requires-Dist: vectorize-client>=0.1.3
